flake8_final/__init__.py
flake8_final/entry.py
flake8_final/py.typed
flake8_final-0.0.3.dist-info/LICENSE
flake8_final-0.0.3.dist-info/METADATA
flake8_final-0.0.3.dist-info/WHEEL
flake8_final-0.0.3.dist-info/entry_points.txt
flake8_final-0.0.3.dist-info/RECORD
